{"title":"Sasami@Nonchasbatta – 10","tags":"Sasami-san@Ganbaranai, Serie in corso","author":"H e l l","date":"30/6/2013","text":"<div class=\"entry-content\">\n\t\t\t\t\t\t<p><img class=\"size-full wp-image-410 alignleft\" title=\"http://www.omnivium.it/wp-content/uploads/2013/05/Nonchosbatta_Sasami-san@Ganbaranai_-_10_TBSH.264_720pAAC_2.0Hi10P4EE5504F.mkv_snapshot_01.05_2013.06.30_01.07.54.png\" src=\"http://www.omnivium.it/wp-content/uploads/2013/05/Nonchosbatta_Sasami-san@Ganbaranai_-_10_TBSH.264_720pAAC_2.0Hi10P4EE5504F.mkv_snapshot_01.05_2013.06.30_01.07.54.png\" alt=\"\" width=\"640\" height=\"360\"></p>\n<p>HABEMUS SASAMI, now with Boku no Pico.</p>\n<p><strong>Dettagli tecnici:</strong></p>\n<p>Sorgente video: TS (TBS)<br>\nRisoluzione: 1280×720<br>\nContainer: MKV<br>\nCodec video: H264-Hi10P<br>\nCodec audio: AAC LC<br>\nSottotitoli: Softsub in ASS<br>\nDimensione: 280.565.729 byte (267.56 MB)<br>\nCRC: F329C613</p>\n<p style=\"text-align: center;\"><strong>Download:</strong></p>\n<p style=\"text-align: center;\"><a title=\"Torrent\" href=\"http://akuma-subs.com/tracker/download.php?id=50a80d639cc7a4e9ed3f6526ef44de0dcd73bb60&amp;f=Sasami-san%40Ganbaranai+10.torrent\">Torrent</a></p>\n"}